catllm/CERAD_functions.py
catllm/__about__.py
catllm/__init__.py
catllm/_providers.py
catllm/_utils.py
catllm/circle_classifier.py
catllm/classify.py
catllm/extract.py
catllm/image_functions.py
catllm/main.py
catllm/model_reference_list.py
catllm/pdf_functions.py
catllm/summarize.py
catllm/text_functions.py
catllm/text_functions_ensemble.py
catllm/calls/CoVe.py
catllm/calls/__init__.py
catllm/calls/all_calls.py
catllm/calls/image_CoVe.py
catllm/calls/image_stepback.py
catllm/calls/pdf_CoVe.py
catllm/calls/pdf_stepback.py
catllm/calls/stepback.py
catllm/calls/top_n.py
catllm/images/circle.png
catllm/images/cube.png
catllm/images/diamond.png
catllm/images/overlapping_pentagons.png
catllm/images/rectangles.png
catllm/old_code/text_functions_old.py
cat_llm-2.1.0.dist-info/METADATA
cat_llm-2.1.0.dist-info/WHEEL
cat_llm-2.1.0.dist-info/licenses/LICENSE
cat_llm-2.1.0.dist-info/RECORD
