Metadata-Version: 2.4
Name: cat-llm
Version: 2.1.0
Summary: A tool for categorizing text data and images using LLMs and vision models
Project-URL: Documentation, https://github.com/chrissoria/cat-llm#readme
Project-URL: Issues, https://github.com/chrissoria/cat-llm/issues
Project-URL: Source, https://github.com/chrissoria/cat-llm
Author-email: Chris Soria <chrissoria@berkeley.edu>
License-Expression: MIT
License-File: LICENSE
Keywords: categorizer,image classification,llm,structured output,survey data,text classification
Classifier: Development Status :: 4 - Beta
Classifier: Programming Language :: Python
Classifier: Programming Language :: Python :: 3.8
Classifier: Programming Language :: Python :: 3.9
Classifier: Programming Language :: Python :: 3.10
Classifier: Programming Language :: Python :: 3.11
Classifier: Programming Language :: Python :: 3.12
Classifier: Programming Language :: Python :: Implementation :: CPython
Classifier: Programming Language :: Python :: Implementation :: PyPy
Requires-Python: >=3.8
Requires-Dist: anthropic
Requires-Dist: openai
Requires-Dist: pandas
Requires-Dist: perplexityai
Requires-Dist: requests
Requires-Dist: tqdm
Provides-Extra: pdf
Requires-Dist: pymupdf>=1.23.0; extra == 'pdf'
